chinpo_tatsuya/__init__.py
chinpo_tatsuya/tatsuya.py
chinpo_tatsuya-0.1.0.dist-info/METADATA
chinpo_tatsuya-0.1.0.dist-info/WHEEL
chinpo_tatsuya-0.1.0.dist-info/top_level.txt
chinpo_tatsuya-0.1.0.dist-info/RECORD
