Metadata-Version: 2.1
Name: chinpo_tatsuya
Version: 0.1.0
Summary: the number of tatsuya
Author: kutowa
Author-email: you@example.com
Classifier: Programming Language :: Python :: 3
Classifier: License :: OSI Approved :: MIT License
Classifier: Operating System :: OS Independent
Requires-Python: >=3.6
